datagrep/__init__.py
datagrep/__main__.py
datagrep/main.py
datagrep/platform/__init__.py
datagrep/platform/__main__.py
datagrep/platform/main.py
datagrep-3.0.0.dist-info/entry_points.txt
datagrep-3.0.0.dist-info/WHEEL
datagrep-3.0.0.dist-info/METADATA
datagrep-3.0.0.dist-info/RECORD
