Metadata-Version: 2.1
Name: datagrep
Version: 3.0.0
Summary: The datagrep CLI.
Author: Michael Schock
Author-email: m@mjschock.com
Requires-Python: >=3.7,<4.0
Classifier: Programming Language :: Python :: 3
Classifier: Programming Language :: Python :: 3.7
Classifier: Programming Language :: Python :: 3.8
Classifier: Programming Language :: Python :: 3.9
Requires-Dist: typer[all] (>=0.4.0,<0.5.0)
